compleat
