Metadata-Version: 1.1
Name: compleat
Version: 0.0.2
Summary: Fetch autocomplete suggestions from Google Search. Use responsibly. Not affiliated with Google.
Home-page: http://github.com/jsvine/compleat/
Author: Jeremy Singer-Vine
Author-email: jsvine@gmail.com
License: MIT
Keywords: autocomplete google search
Platform: UNKNOWN
Classifier: Development Status :: 3 - Alpha
Classifier: Intended Audience :: Developers
Classifier: License :: OSI Approved :: MIT License
Classifier: Operating System :: OS Independent
Classifier: Programming Language :: Python :: 2.6
Classifier: Programming Language :: Python :: 2.7
Classifier: Programming Language :: Python :: 3.3
